autoscrub/__init__.py
autoscrub/__version__.py
autoscrub/scripts/__init__.py
autoscrub/scripts/cli.py
docs/__init__.py
docs/conf.py
autoscrub-0.7.5.dist-info/COPYING
autoscrub-0.7.5.dist-info/METADATA
autoscrub-0.7.5.dist-info/WHEEL
autoscrub-0.7.5.dist-info/entry_points.txt
autoscrub-0.7.5.dist-info/top_level.txt
autoscrub-0.7.5.dist-info/RECORD
